diself/__init__.py
diself/diself.py
diself-1.0.1.dist-info/LICENSE
diself-1.0.1.dist-info/METADATA
diself-1.0.1.dist-info/WHEEL
diself-1.0.1.dist-info/top_level.txt
diself-1.0.1.dist-info/RECORD
