Metadata-Version: 2.1
Name: diself
Version: 1.0.1
Summary: A python module like discord.py but for selfbot
Home-page: https://github.com/lululepu/diself
Author: Lululepu
Author-email: a.no.qsdf@gmail.com
License: MIT
License-File: LICENSE
Requires-Dist: websocket-client
Requires-Dist: requests
